{
    "configurations": [
        {
            "name": "x64-Debug",
            "generator": "Ninja",
            "configurationType": "Debug",
            "inheritEnvironments": [ "msvc_x64_x64" ],
            "buildRoot": "${projectDir}\\out\\build\\${name}",
            "installRoot": "${projectDir}\\out\\install\\${name}",
            "cmakeCommandArgs": "",
            "buildCommandArgs": "",
            "ctestCommandArgs": "",
            "cmakeExecutable": "C:/Program Files/CMake/bin/cmake.exe",
            "intelliSenseMode": "windows-msvc-x64",
            "variables": [
                {
                    "name": "BUILD_DX12",
                    "value": "True",
                    "type": "BOOL"
                },
                {
                    "name": "USE_OPENGLES3",
                    "value": "True",
                    "type": "BOOL"
                },
                {
                    "name": "USE_OPENGLES2",
                    "value": "False",
                    "type": "BOOL"
                }
            ]
        }
    ]
}